{
    "title": "Daily Devotional",
    "subtitle": "January 24th, %%year%%",
    "subtitle2": "by Larry Stockstill",
    "navigation": [
        {
            "ref": "devotion",
            "value": "Daily Devotional"
        },
        {
            "ref": "ot-passage",
            "value": "Old Testament"
        },
        {
            "ref": "nt-passage",
            "value": "New Testament"
        },
        {
            "ref": "ps-passage",
            "value": "Psalms"
        },
        {
            "ref": "pr-passage",
            "value": "Proverbs"
        }
    ],
    "content": [
        {
            "id": "devotion",
            "type": "devotion",
            "title": "Daily Devotional",
            "value": "%3Cp%3EIsrael's%20blessings%20started%20with%20the%20word%20may.%20As%20Jacob%20laid%20his%20hands%20upon%20the%20heads%20of%20Ephraim%20and%20Manasseh%2C%20he%20uttered%20the%20word%20and%20invoked%20a%20blessing%20with%20it%20three%20times.%20%3Cbr%3E%3Cbr%3EThe%20psalmist%20blessed%20Israel%20with%20equal%20force%3A%20%22May%20the%20Lord%20respond%20to%20your%20cry.%20May%20the%20God%20of%20Israel%20keep%20you%20safe.%20.%20.%20.%20May%20he%20send%20you%20help.%20.%20.%20.%20May%20he%20remember%20all%20your%20gifts.%20.%20.%20.%20May%20he%20grant%20your%20heart's%20desire%20and%20fulfill%20all%20your%20plans.%20May%20we%20shout%20for%20joy%20when%20we%20hear%20of%20your%20victory.%20.%20.%20.%20May%20the%20Lord%20answer%20all%20your%20prayers%22%20(Psalm%2020%3A1-5).%20%3Cbr%3E%3Cbr%3EThe%20word%20may%20could%20be%20translated%20%22allow.%22%20In%20other%20words%2C%20allow%20God%20to%20do%20what%20He%20wants%20to%20do%20for%20you.%20You%20must%20settle%20in%20your%20mind%20forever%20that%20God%20wants%20to%20bless%20you.%20Any%20doubt%20will%20always%20result%20in%20questioning%20His%20desire%20to%20answer%20your%20prayers%20or%20to%20increase%2C%20deliver%2C%20and%20help%20you.%20%3Cbr%3E%3Cbr%3EGod's%20Word%20has%20the%20same%20power%20to%20bless%20you%2C%20as%20did%20Jacob's%20words%20for%20his%20grandsons.%20%22Pay%20attention%2C%20my%20child%2C%20to%20what%20I%20say.%20Listen%20carefully.%20Don't%20lose%20sight%20of%20my%20words.%20Let%20them%20penetrate%20deep%20within%20your%20heart%2C%20for%20they%20bring%20life%20and%20radiant%20health%20to%20anyone%20who%20discovers%20their%20meaning%22%20(Proverbs%204%3A20-22).%20%3Cbr%3E%3Cbr%3EMay%20the%20Lord%20bless%20you%20today!%20%3C%2Fp%3E%0A"
        },
        {
            "id": "ot-passage",
            "type": "passage",
            "title": "Old Testament Reading",
            "api_nlt_to_ref": "Genesis.48:1-49:33",
            "value": "%3Cdiv%20class%3D%22%20NLT%20NLT%20BibleText%20section%22%3E%3Csection%3E%3Ch2%20class%3D%22bk_ch_vs_header%22%3EGenesis%2048%3A1-49%3A33%2C%20NLT%3C%2Fh2%3E%3Cverse_export%20orig%3D%22gene_48_1%22%20bk%3D%22gene%22%20ch%3D%2248%22%20vn%3D%221%22%3E%0A%3Cp%20class%3D%22chapter-number%22%3E%3Cspan%20class%3D%22cw%22%3EGenesis%3C%2Fspan%3E%26%23xA0%3B%3Cspan%20class%3D%22cw_ch%22%3E48%3C%2Fspan%3E%3C%2Fp%3E%0A%3Cp%20class%3D%22subhead%22%3EJacob%20Blesses%20Manasseh%20and%20Ephraim%3C%2Fp%3E%0A%3Cp%20class%3D%22body-ch-hd%22%3E%3Cspan%20class%3D%22vn%22%3E1%3C%2Fspan%3EOne%20day%20not%20long%20after%20this%2C%20word%20came%20to%20Joseph%2C%20%26%23x201C%3BYour%20father%20is%20failing%20rapidly.%26%23x201D%3B%20So%20Joseph%20went%20to%20visit%20his%20father%2C%20and%20he%20took%20with%20him%20his%20two%20sons%2C%20Manasseh%20and%20Ephraim.%3C%2Fp%3E%0A%3C%2Fverse_export%3E%3Cverse_export%20orig%3D%22gene_48_2%22%20bk%3D%22gene%22%20ch%3D%2248%22%20vn%3D%222%22%3E%0A%3Cp%20class%3D%22body%22%3E%3Cspan%20class%3D%22vn%22%3E2%3C%2Fspan%3EWhen%20Joseph%20arrived%2C%20Jacob%20was%20told%2C%20%26%23x201C%3BYour%20son%20Joseph%20has%20come%20to%20see%20you.%26%23x201D%3B%20So%20Jacob%3Ca%20class%3D%22a-tn%22%3E*%3C%2Fa%3E%3Cspan%20class%3D%22tn%22%3E%3Cspan%20class%3D%22tn-ref%22%3E48%3A2%3C%2Fspan%3E%20Hebrew%20%3Cem%3EIsrael%3B%3C%2Fem%3E%20also%20in%2048%3A8%2C%2010%2C%2011%2C%2013%2C%2014%2C%2021.%20See%20note%20on%2035%3A21.%3C%2Fspan%3E%20gathered%20his%20strength%20and%20sat%20up%20in%20his%20bed.%3C%2Fp%3E%0A%3C%2Fverse_export%3E%3Cverse_export%20orig%3D%22gene_48_3%22%20bk%3D%22gene%22%20ch%3D%2248%22%20vn%3D%223%22%3E%0A%3Cp%20class%3D%22body%22%3E%3Cspan%20class%3D%22vn%22%3E3%3C%2Fspan%3EJacob%20said%20to%20Joseph%2C%20%26%23x201C%3BGod%20Almighty%3Ca%20class%3D%22a-tn%22%3E*%3C%2Fa%3E%3Cspan%20class%3D%22tn%22%3E%3Cspan%20class%3D%22tn-ref%22%3E48%3A3%3C%2Fspan%3E%20Hebrew%20%3Cem%3EEl-Shaddai.%3C%2Fem%3E%3C%2Fspan%3E%20appeared%20to%20me%20at%20Luz%20in%20the%20land%20of%20Canaan%20and%20blessed%20me.%20%3Cverse_export%20orig%3D%22gene_48_4%22%20bk%3D%22gene%22%20ch%3D%2248%22%20vn%3D%224%22%3E%3Cspan%20class%3D%22vn%22%3E4%3C%2Fspan%3EHe%20said%20to%20me%2C%20%26%23x2018%3BI%20will%20make%20you%20fruitful%2C%20and%20I%20will%20multiply%20your%20descendants.%20I%20will%20make%20you%20a%20multitude%20of%20nations.%20And%20I%20will%20give%20this%20land%20of%20Canaan%20to%20your%20descendants%3Ca%20class%3D%22a-tn%22%3E*%3C%2Fa%3E%3Cspan%20class%3D%22tn%22%3E%3Cspan%20class%3D%22tn-ref%22%3E48%3A4%3C%2Fspan%3E%20Hebrew%20%3Cem%3Eseed%3B%3C%2Fem%3E%20also%20in%2048%3A19.%3C%2Fspan%3E%20after%20you%20as%20an%20everlasting%20possession.%26%23x2019%3B%3C%2Fverse_export%3E%3C%2Fp%3E%3Cp%3E%0A%3Cverse_export%20orig%3D%22gene_48_5%22%20bk%3D%22gene%22%20ch%3D%2248%22%20vn%3D%225%22%3E%0A%3C%2Fverse_export%3E%3C%2Fp%3E%3Cp%20class%3D%22body%22%3E%3Cspan%20class%3D%22vn%22%3E5%3C%2Fspan%3E%26%23x201C%3BNow%20I%20am%20claiming%20as%20my%20own%20sons%20these%20two%20boys%20of%20yours%2C%20Ephraim%20and%20Manasseh%2C%20who%20were%20born%20here%20in%20the%20land%20of%20Egypt%20before%20I%20arrived.%20They%20will%20be%20my%20sons%2C%20just%20as%20Reuben%20and%20Simeon%20are.%20%3Cverse_export%20orig%3D%22gene_48_6%22%20bk%3D%22gene%22%20ch%3D%2248%22%20vn%3D%226%22%3E%3Cspan%20class%3D%22vn%22%3E6%3C%2Fspan%3EBut%20any%20children%20born%20to%20you%20in%20the%20future%20will%20be%20your%20own%2C%20and%20they%20will%20inherit%20land%20within%20the%20territories%20of%20their%20brothers%20Ephraim%20and%20Manasseh.%3C%2Fverse_export%3E%3C%2Fp%3E%3Cp%3E%0A%3Cverse_export%20orig%3D%22gene_48_7%22%20bk%3D%22gene%22%20ch%3D%2248%22%20vn%3D%227%22%3E%0A%3C%2Fverse_export%3E%3C%2Fp%3E%3Cp%20class%3D%22body%22%3E%3Cspan%20class%3D%22vn%22%3E7%3C%2Fspan%3E%26%23x201C%3BLong%20ago%2C%20as%20I%20was%20returning%20from%20Paddan-aram%2C%3Ca%20class%3D%22a-tn%22%3E*%3C%2Fa%3E%3Cspan%20class%3D%22tn%22%3E%3Cspan%20class%3D%22tn-ref%22%3E48%3A7%3C%2Fspan%3E%20Hebrew%20%3Cem%3EPaddan%2C%3C%2Fem%3E%20referring%20to%20Paddan-aram%3B%20compare%20Gen%2035%3A9.%3C%2Fspan%3E%20Rachel%20died%20in%20the%20land%20of%20Canaan.%20We%20were%20still%20on%20the%20way%2C%20some%20distance%20from%20Ephrath%20(that%20is%2C%20Bethlehem).%20So%20with%20great%20sorrow%20I%20buried%20her%20there%20beside%20the%20road%20to%20Ephrath.%26%23x201D%3B%3C%2Fp%3E%0A%3C%2Fverse_export%3E%3Cverse_export%20orig%3D%22gene_48_8%22%20bk%3D%22gene%22%20ch%3D%2248%22%20vn%3D%228%22%3E%0A%3Cp%20class%3D%22body%22%3E%3Cspan%20class%3D%22vn%22%3E8%3C%2Fspan%3EThen%20Jacob%20looked%20over%20at%20the%20two%20boys.%20%26%23x201C%3BAre%20these%20your%20sons%3F%26%23x201D%3B%20he%20asked.%3C%2Fp%3E%0A%3C%2Fverse_export%3E%3Cverse_export%20orig%3D%22gene_48_9%22%20bk%3D%22gene%22%20ch%3D%2248%22%20vn%3D%229%22%3E%0A%3Cp%20class%3D%22body%22%3E%3Cspan%20class%3D%22vn%22%3E9%3C%2Fspan%3E%26%23x201C%3BYes%2C%26%23x201D%3B%20Joseph%20told%20him%2C%20%26%23x201C%3Bthese%20are%20the%20sons%20God%20has%20given%20me%20here%20in%20Egypt.%26%23x201D%3B%3C%2Fp%3E%0A%3Cp%20class%3D%22body%22%3EAnd%20Jacob%20said%2C%20%26%23x201C%3BBring%20them%20closer%20to%20me%2C%20so%20I%20can%20bless%20them.%26%23x201D%3B%3C%2Fp%3E%0A%3C%2Fverse_export%3E%3Cverse_export%20orig%3D%22gene_48_10%22%20bk%3D%22gene%22%20ch%3D%2248%22%20vn%3D%2210%22%3E%0A%3Cp%20class%3D%22body%22%3E%3Cspan%20class%3D%22vn%22%3E10%3C%2Fspan%3EJacob%20was%20half%20blind%20because%20of%20his%20age%20and%20could%20hardly%20see.%20So%20Joseph%20brought%20the%20boys%20close%20to%20him%2C%20and%20Jacob%20kissed%20and%20embraced%20them.%20%3Cverse_export%20orig%3D%22gene_48_11%22%20bk%3D%22gene%22%20ch%3D%2248%22%20vn%3D%2211%22%3E%3Cspan%20class%3D%22vn%22%3E11%3C%2Fspan%3EThen%20Jacob%20said%20to%20Joseph%2C%20%26%23x201C%3BI%20never%20thought%20I%20would%20see%20your%20face%20again%2C%20but%20now%20God%20has%20let%20me%20see%20your%20children%2C%20too!%26%23x201D%3B%3C%2Fverse_export%3E%3C%2Fp%3E%3Cp%3E%0A%3Cverse_export%20orig%3D%22gene_48_12%22%20bk%3D%22gene%22%20ch%3D%2248%22%20vn%3D%2212%22%3E%0A%3C%2Fverse_export%3E%3C%2Fp%3E%3Cp%20class%3D%22body%22%3E%3Cspan%20class%3D%22vn%22%3E12%3C%2Fspan%3EJoseph%20moved%20the%20boys%2C%20who%20were%20at%20their%20grandfather%26%23x2019%3Bs%20knees%2C%20and%20he%20bowed%20with%20his%20face%20to%20the%20ground.%20%3Cverse_export%20orig%3D%22gene_48_13%22%20bk%3D%22gene%22%20ch%3D%2248%22%20vn%3D%2213%22%3E%3Cspan%20class%3D%22vn%22%3E13%3C%2Fspan%3EThen%20he%20positioned%20the%20boys%20in%20front%20of%20Jacob.%20With%20his%20right%20hand%20he%20directed%20Ephraim%20toward%20Jacob%26%23x2019%3Bs%20left%20hand%2C%20and%20with%20his%20left%20hand%20he%20put%20Manasseh%20at%20Jacob%26%23x2019%3Bs%20right%20hand.%20%3C%2Fverse_export%3E%3Cverse_export%20orig%3D%22gene_48_14%22%20bk%3D%22gene%22%20ch%3D%2248%22%20vn%3D%2214%22%3E%3Cspan%20class%3D%22vn%22%3E14%3C%2Fspan%3EBut%20Jacob%20crossed%20his%20arms%20as%20he%20reached%20out%20to%20lay%20his%20hands%20on%20the%20boys%26%23x2019%3B%20heads.%20He%20put%20his%20right%20hand%20on%20the%20head%20of%20Ephraim%2C%20though%20he%20was%20the%20younger%20boy%2C%20and%20his%20left%20hand%20on%20the%20head%20of%20Manasseh%2C%20though%20he%20was%20the%20firstborn.%20%3C%2Fverse_export%3E%3Cverse_export%20orig%3D%22gene_48_15%22%20bk%3D%22gene%22%20ch%3D%2248%22%20vn%3D%2215%22%3E%3Cspan%20class%3D%22vn%22%3E15%3C%2Fspan%3EThen%20he%20blessed%20Joseph%20and%20said%2C%3C%2Fverse_export%3E%3C%2Fp%3E%3Cp%3E%0A%3C%2Fp%3E%3Cp%20class%3D%22poet1-sp%22%3E%26%23x201C%3BMay%20the%20God%20before%20whom%20my%20grandfather%20Abraham%3C%2Fp%3E%0A%3Cp%20class%3D%22poet2%22%3Eand%20my%20father%2C%20Isaac%2C%20walked%26%23x2014%3B%3C%2Fp%3E%0A%3Cp%20class%3D%22poet1%22%3Ethe%20God%20who%20has%20been%20my%20shepherd%3C%2Fp%3E%0A%3Cp%20class%3D%22poet2%22%3Eall%20my%20life%2C%20to%20this%20very%20day%2C%3C%2Fp%3E%0A%3C%2Fverse_export%3E%3Cverse_export%20orig%3D%22gene_48_16%22%20bk%3D%22gene%22%20ch%3D%2248%22%20vn%3D%2216%22%3E%0A%3Cp%20class%3D%22poet1-vn%22%3E%3Cspan%20class%3D%22vn%22%3E16%3C%2Fspan%3Ethe%20Angel%20who%20has%20redeemed%20me%20from%20all%20harm%26%23x2014%3B%3C%2Fp%3E%0A%3Cp%20class%3D%22poet2%22%3Emay%20he%20bless%20these%20boys.%3C%2Fp%3E%0A%3Cp%20class%3D%22poet1%22%3EMay%20they%20preserve%20my%20name%3C%2Fp%3E%0A%3Cp%20class%3D%22poet2%22%3Eand%20the%20names%20of%20Abraham%20and%20Isaac.%3C%2Fp%3E%0A%3Cp%20class%3D%22poet1%22%3EAnd%20may%20their%20descendants%20multiply%20greatly%3C%2Fp%3E%0A%3Cp%20class%3D%22poet2%22%3Ethroughout%20the%20earth.%26%23x201D%3B%3C%2Fp%3E%0A%3C%2Fverse_export%3E%3Cverse_export%20orig%3D%22gene_48_17%22%20bk%3D%22gene%22%20ch%3D%2248%22%20vn%3D%2217%22%3E%0A%3Cp%20class%3D%22body-sp%22%3E%3Cspan%20class%3D%22vn%22%3E17%3C%2Fspan%3EBut%20Joseph%20was%20upset%20when%20he%20saw%20that%20his%20father%20placed%20his%20right%20hand%20on%20Ephraim%26%23x2019%3Bs%20head.%20So%20Joseph%20lifted%20it%20to%20move%20it%20from%20Ephraim%26%23x2019%3Bs%20head%20to%20Manasseh%26%23x2019%3Bs%20head.%20%3Cverse_export%20orig%3D%22gene_48_18%22%20bk%3D%22gene%22%20ch%3D%2248%22%20vn%3D%2218%22%3E%3Cspan%20class%3D%22vn%22%3E18%3C%2Fspan%3E%26%23x201C%3BNo%2C%20my%20father%2C%26%23x201D%3B%20he%20said.%20%26%23x201C%3BThis%20one%20is%20the%20firstborn.%20Put%20your%20right%20hand%20on%20his%20head.%26%23x201D%3B%3C%2Fverse_export%3E%3C%2Fp%3E%3Cp%3E%0A%3Cverse_export%20orig%3D%22gene_48_19%22%20bk%3D%22gene%22%20ch%3D%2248%22%20vn%3D%2219%22%3E%0A%3C%2Fverse_export%3E%3C%2Fp%3E%3Cp%20class%3D%22body%22%3E%3Cspan%20class%3D%22vn%22%3E19%3C%2Fspan%3EBut%20his%20father%20refused.%20%26%23x201C%3BI%20know%2C%20my%20son%3B%20I%20know%2C%26%23x201D%3B%20he%20replied.%20%26%23x201C%3BManasseh%20will%20also%20become%20a%20great%20people%2C%20but%20his%20younger%20brother%20will%20become%20even%20greater.%20And%20his%20descendants%20will%20become%20a%20multitude%20of%20nations.%26%23x201D%3B%3C%2Fp%3E%0A%3C%2Fverse_export%3E%3Cverse_export%20orig%3D%22gene_48_20%22%20bk%3D%22gene%22%20ch%3D%2248%22%20vn%3D%2220%22%3E%0A%3Cp%20class%3D%22body%22%3E%3Cspan%20class%3D%22vn%22%3E20%3C%2Fspan%3ESo%20Jacob%20blessed%20the%20boys%20that%20day%20with%20this%20blessing%3A%20%26%23x201C%3BThe%20people%20of%20Israel%20will%20use%20your%20names%20when%20they%20give%20a%20blessing.%20They%20will%20say%2C%20%26%23x2018%3BMay%20God%20make%20you%20as%20prosperous%20as%20Ephraim%20and%20Manasseh.%26%23x2019%3B%26%23x201D%3B%20In%20this%20way%2C%20Jacob%20put%20Ephraim%20ahead%20of%20Manasseh.%3C%2Fp%3E%0A%3C%2Fverse_export%3E%3Cverse_export%20orig%3D%22gene_48_21%22%20bk%3D%22gene%22%20ch%3D%2248%22%20vn%3D%2221%22%3E%0A%3Cp%20class%3D%22body%22%3E%3Cspan%20class%3D%22vn%22%3E21%3C%2Fspan%3EThen%20Jacob%20said%20to%20Joseph%2C%20%26%23x201C%3BLook%2C%20I%20am%20about%20to%20die%2C%20but%20God%20will%20be%20with%20you%20and%20will%20take%20you%20back%20to%20Canaan%2C%20the%20land%20of%20your%20ancestors.%20%3Cverse_export%20orig%3D%22gene_48_22%22%20bk%3D%22gene%22%20ch%3D%2248%22%20vn%3D%2222%22%3E%3Cspan%20class%3D%22vn%22%3E22%3C%2Fspan%3EAnd%20beyond%20what%20I%20have%20given%20your%20brothers%2C%20I%20am%20giving%20you%20an%20extra%20portion%20of%20the%20land%3Ca%20class%3D%22a-tn%22%3E*%3C%2Fa%3E%3Cspan%20class%3D%22tn%22%3E%3Cspan%20class%3D%22tn-ref%22%3E48%3A22%3C%2Fspan%3E%20Or%20%3Cem%3Ean%20extra%20ridge%20of%20land.%3C%2Fem%3E%20The%20meaning%20of%20the%20Hebrew%20is%20uncertain.%3C%2Fspan%3E%20that%20I%20took%20from%20the%20Amorites%20with%20my%20sword%20and%20bow.%26%23x201D%3B%3C%2Fverse_export%3E%3C%2Fp%3E%3Cp%3E%0A%3Cverse_export%20orig%3D%22gene_49_1%22%20bk%3D%22gene%22%20ch%3D%2249%22%20vn%3D%221%22%3E%0A%3C%2Fverse_export%3E%3C%2Fp%3E%3Cp%20class%3D%22chapter-number%22%3E%3Cspan%20class%3D%22cw%22%3EGenesis%3C%2Fspan%3E%26%23xA0%3B%3Cspan%20class%3D%22cw_ch%22%3E49%3C%2Fspan%3E%3C%2Fp%3E%0A%3Cp%20class%3D%22subhead%22%3EJacob%26%23x2019%3Bs%20Last%20Words%20to%20His%20Sons%3C%2Fp%3E%0A%3Cp%20class%3D%22body-ch-hd%22%3E%3Cspan%20class%3D%22vn%22%3E1%3C%2Fspan%3EThen%20Jacob%20called%20together%20all%20his%20sons%20and%20said%2C%20%26%23x201C%3BGather%20around%20me%2C%20and%20I%20will%20tell%20you%20what%20will%20happen%20to%20each%20of%20you%20in%20the%20days%20to%20come.%3C%2Fp%3E%0A%3C%2Fverse_export%3E%3Cverse_export%20orig%3D%22gene_49_2%22%20bk%3D%22gene%22%20ch%3D%2249%22%20vn%3D%222%22%3E%0A%3Cp%20class%3D%22poet1-vn-sp%22%3E%3Cspan%20class%3D%22vn%22%3E2%3C%2Fspan%3E%26%23x201C%3BCome%20and%20listen%2C%20you%26%23xA0%3Bsons%20of%20Jacob%3B%3C%2Fp%3E%0A%3Cp%20class%3D%22poet2%22%3Elisten%20to%20Israel%2C%20your%20father.%3C%2Fp%3E%0A%3C%2Fverse_export%3E%3Cverse_export%20orig%3D%22gene_49_3%22%20bk%3D%22gene%22%20ch%3D%2249%22%20vn%3D%223%22%3E%0A%3Cp%20class%3D%22poet1-vn-sp%22%3E%3Cspan%20class%3D%22vn%22%3E3%3C%2Fspan%3E%26%23x201C%3BReuben%2C%20you%20are%20my%20firstborn%2C%20my%20strength%2C%3C%2Fp%3E%0A%3Cp%20class%3D%22poet2%22%3Ethe%20child%20of%20my%20vigorous%20youth.%3C%2Fp%3E%0A%3Cp%20class%3D%22poet2%22%3EYou%20are%20first%20in%20rank%20and%20first%20in%20power.%3C%2Fp%3E%0A%3C%2Fverse_export%3E%3Cverse_export%20orig%3D%22gene_49_4%22%20bk%3D%22gene%22%20ch%3D%2249%22%20vn%3D%224%22%3E%0A%3Cp%20class%3D%22poet1-vn%22%3E%3Cspan%20class%3D%22vn%22%3E4%3C%2Fspan%3EBut%20you%20are%20as%20unruly%20as%20a%20flood%2C%3C%2Fp%3E%0A%3Cp%20class%3D%22poet2%22%3Eand%20you%20will%20be%20first%20no%20longer.%3C%2Fp%3E%0A%3Cp%20class%3D%22poet1%22%3EFor%20you%20went%20to%20bed%20with%20my%20wife%3B%3C%2Fp%3E%0A%3Cp%20class%3D%22poet2%22%3Eyou%20defiled%20my%20marriage%20couch.%3C%2Fp%3E%0A%3C%2Fverse_export%3E%3Cverse_export%20orig%3D%22gene_49_5%22%20bk%3D%22gene%22%20ch%3D%2249%22%20vn%3D%225%22%3E%0A%3Cp%20class%3D%22poet1-vn-sp%22%3E%3Cspan%20class%3D%22vn%22%3E5%3C%2Fspan%3E%26%23x201C%3BSimeon%20and%20Levi%20are%20two%20of%20a%20kind%3B%3C%2Fp%3E%0A%3Cp%20class%3D%22poet2%22%3Etheir%20weapons%20are%20instruments%20of%20violence.%3C%2Fp%3E%0A%3C%2Fverse_export%3E%3Cverse_export%20orig%3D%22gene_49_6%22%20bk%3D%22gene%22%20ch%3D%2249%22%20vn%3D%226%22%3E%0A%3Cp%20class%3D%22poet1-vn%22%3E%3Cspan%20class%3D%22vn%22%3E6%3C%2Fspan%3EMay%20I%20never%20join%20in%20their%20meetings%3B%3C%2Fp%3E%0A%3Cp%20class%3D%22poet2%22%3Emay%20I%20never%20be%20a%20party%20to%20their%20plans.%3C%2Fp%3E%0A%3Cp%20class%3D%22poet1%22%3EFor%20in%20their%20anger%20they%20murdered%20men%2C%3C%2Fp%3E%0A%3Cp%20class%3D%22poet2%22%3Eand%20they%20crippled%20oxen%20just%20for%20sport.%3C%2Fp%3E%0A%3C%2Fverse_export%3E%3Cverse_export%20orig%3D%22gene_49_7%22%20bk%3D%22gene%22%20ch%3D%2249%22%20vn%3D%227%22%3E%0A%3Cp%20class%3D%22poet1-vn%22%3E%3Cspan%20class%3D%22vn%22%3E7%3C%2Fspan%3EA%20curse%20on%20their%20anger%2C%20for%20it%20is%20fierce%3B%3C%2Fp%3E%0A%3Cp%20class%3D%22poet2%22%3Ea%20curse%20on%20their%20wrath%2C%20for%20it%20is%20cruel.%3C%2Fp%3E%0A%3Cp%20class%3D%22poet1%22%3EI%20will%20scatter%20them%20among%20the%20descendants%20of%20Jacob%3B%3C%2Fp%3E%0A%3Cp%20class%3D%22poet2%22%3EI%20will%20disperse%20them%20throughout%20Israel.%3C%2Fp%3E%0A%3C%2Fverse_export%3E%3Cverse_export%20orig%3D%22gene_49_8%22%20bk%3D%22gene%22%20ch%3D%2249%22%20vn%3D%228%22%3E%0A%3Cp%20class%3D%22poet1-vn-sp%22%3E%3Cspan%20class%3D%22vn%22%3E8%3C%2Fspan%3E%26%23x201C%3BJudah%2C%20your%20brothers%20will%20praise%20you.%3C%2Fp%3E%0A%3Cp%20class%3D%22poet2%22%3EYou%20will%20grasp%20your%20enemies%20by%20the%20neck.%3C%2Fp%3E%0A%3Cp%20class%3D%22poet2%22%3EAll%20your%20relatives%20will%20bow%20before%20you.%3C%2Fp%3E%0A%3C%2Fverse_export%3E%3Cverse_export%20orig%3D%22gene_49_9%22%20bk%3D%22gene%22%20ch%3D%2249%22%20vn%3D%229%22%3E%0A%3Cp%20class%3D%22poet1-vn%22%3E%3Cspan%20class%3D%22vn%22%3E9%3C%2Fspan%3EJudah%2C%20my%20son%2C%20is%20a%20young%20lion%3C%2Fp%3E%0A%3Cp%20class%3D%22poet2%22%3Ethat%20has%20finished%20eating%20its%20prey.%3C%2Fp%3E%0A%3Cp%20class%3D%22poet1%22%3ELike%20a%20lion%20he%20crouches%20and%20lies%20down%3B%3C%2Fp%3E%0A%3Cp%20class%3D%22poet2%22%3Elike%20a%20lioness%26%23x2014%3Bwho%20dares%20to%20rouse%20him%3F%3C%2Fp%3E%0A%3C%2Fverse_export%3E%3Cverse_export%20orig%3D%22gene_49_10%22%20bk%3D%22gene%22%20ch%3D%2249%22%20vn%3D%2210%22%3E%0A%3Cp%20class%3D%22poet1-vn%22%3E%3Cspan%20class%3D%22vn%22%3E10%3C%2Fspan%3EThe%20scepter%20will%20not%20depart%20from%20Judah%2C%3C%2Fp%3E%0A%3Cp%20class%3D%22poet2%22%3Enor%20the%20ruler%26%23x2019%3Bs%20staff%20from%20his%20descendants%2C%3Ca%20class%3D%22a-tn%22%3E*%3C%2Fa%3E%3Cspan%20class%3D%22tn%22%3E%3Cspan%20class%3D%22tn-ref%22%3E49%3A10a%3C%2Fspan%3E%20Hebrew%20%3Cem%3Efrom%20between%20his%20feet.%3C%2Fem%3E%3C%2Fspan%3E%3C%2Fp%3E%0A%3Cp%20class%3D%22poet1%22%3Euntil%20the%20coming%20of%20the%20one%20to%20whom%20it%20belongs%2C%3Ca%20class%3D%22a-tn%22%3E*%3C%2Fa%3E%3Cspan%20class%3D%22tn%22%3E%3Cspan%20class%3D%22tn-ref%22%3E49%3A10b%3C%2Fspan%3E%20Or%20%3Cem%3Euntil%20tribute%20is%20brought%20to%20him%20and%20the%20peoples%20obey%3B%3C%2Fem%3E%20traditionally%20rendered%20%3Cem%3Euntil%20Shiloh%20comes.%3C%2Fem%3E%3C%2Fspan%3E%3C%2Fp%3E%0A%3Cp%20class%3D%22poet2%22%3Ethe%20one%20whom%20all%20nations%20will%20honor.%3C%2Fp%3E%0A%3C%2Fverse_export%3E%3Cverse_export%20orig%3D%22gene_49_11%22%20bk%3D%22gene%22%20ch%3D%2249%22%20vn%3D%2211%22%3E%0A%3Cp%20class%3D%22poet1-vn%22%3E%3Cspan%20class%3D%22vn%22%3E11%3C%2Fspan%3EHe%20ties%20his%20foal%20to%20a%20grapevine%2C%3C%2Fp%3E%0A%3Cp%20class%3D%22poet2%22%3Ethe%20colt%20of%20his%20donkey%20to%20a%20choice%20vine.%3C%2Fp%3E%0A%3Cp%20class%3D%22poet1%22%3EHe%20washes%20his%20clothes%20in%20wine%2C%3C%2Fp%3E%0A%3Cp%20class%3D%22poet2%22%3Ehis%20robes%20in%20the%20blood%20of%20grapes.%3C%2Fp%3E%0A%3C%2Fverse_export%3E%3Cverse_export%20orig%3D%22gene_49_12%22%20bk%3D%22gene%22%20ch%3D%2249%22%20vn%3D%2212%22%3E%0A%3Cp%20class%3D%22poet1-vn%22%3E%3Cspan%20class%3D%22vn%22%3E12%3C%2Fspan%3EHis%20eyes%20are%20darker%20than%20wine%2C%3C%2Fp%3E%0A%3Cp%20class%3D%22poet2%22%3Eand%20his%20teeth%20are%20whiter%20than%20milk.%3C%2Fp%3E%0A%3C%2Fverse_export%3E%3Cverse_export%20orig%3D%22gene_49_13%22%20bk%3D%22gene%22%20ch%3D%2249%22%20vn%3D%2213%22%3E%0A%3Cp%20class%3D%22poet1-vn-sp%22%3E%3Cspan%20class%3D%22vn%22%3E13%3C%2Fspan%3E%26%23x201C%3BZebulun%20will%20settle%20by%20the%20seashore%3C%2Fp%3E%0A%3Cp%20class%3D%22poet2%22%3Eand%20will%20be%20a%20harbor%20for%20ships%3B%3C%2Fp%3E%0A%3Cp%20class%3D%22poet2%22%3Ehis%20borders%20will%20extend%20to%20Sidon.%3C%2Fp%3E%0A%3C%2Fverse_export%3E%3Cverse_export%20orig%3D%22gene_49_14%22%20bk%3D%22gene%22%20ch%3D%2249%22%20vn%3D%2214%22%3E%0A%3Cp%20class%3D%22poet1-vn-sp%22%3E%3Cspan%20class%3D%22vn%22%3E14%3C%2Fspan%3E%26%23x201C%3BIssachar%20is%20a%20sturdy%20donkey%2C%3C%2Fp%3E%0A%3Cp%20class%3D%22poet2%22%3Eresting%20between%20two%20saddlepacks.%3Ca%20class%3D%22a-tn%22%3E*%3C%2Fa%3E%3Cspan%20class%3D%22tn%22%3E%3Cspan%20class%3D%22tn-ref%22%3E49%3A14%3C%2Fspan%3E%20Or%20%3Cem%3Esheepfolds%2C%3C%2Fem%3E%20or%20%3Cem%3Ehearths.%3C%2Fem%3E%3C%2Fspan%3E%3C%2Fp%3E%0A%3C%2Fverse_export%3E%3Cverse_export%20orig%3D%22gene_49_15%22%20bk%3D%22gene%22%20ch%3D%2249%22%20vn%3D%2215%22%3E%0A%3Cp%20class%3D%22poet1-vn%22%3E%3Cspan%20class%3D%22vn%22%3E15%3C%2Fspan%3EWhen%20he%20sees%20how%20good%20the%20countryside%20is%3C%2Fp%3E%0A%3Cp%20class%3D%22poet2%22%3Eand%20how%20pleasant%20the%20land%2C%3C%2Fp%3E%0A%3Cp%20class%3D%22poet1%22%3Ehe%20will%20bend%20his%20shoulder%20to%20the%20load%3C%2Fp%3E%0A%3Cp%20class%3D%22poet2%22%3Eand%20submit%20himself%20to%20hard%20labor.%3C%2Fp%3E%0A%3C%2Fverse_export%3E%3Cverse_export%20orig%3D%22gene_49_16%22%20bk%3D%22gene%22%20ch%3D%2249%22%20vn%3D%2216%22%3E%0A%3Cp%20class%3D%22poet1-vn-sp%22%3E%3Cspan%20class%3D%22vn%22%3E16%3C%2Fspan%3E%26%23x201C%3BDan%20will%20govern%20his%20people%2C%3C%2Fp%3E%0A%3Cp%20class%3D%22poet2%22%3Elike%20any%20other%20tribe%20in%20Israel.%3C%2Fp%3E%0A%3C%2Fverse_export%3E%3Cverse_export%20orig%3D%22gene_49_17%22%20bk%3D%22gene%22%20ch%3D%2249%22%20vn%3D%2217%22%3E%0A%3Cp%20class%3D%22poet1-vn%22%3E%3Cspan%20class%3D%22vn%22%3E17%3C%2Fspan%3EDan%20will%20be%20a%20snake%20beside%20the%20road%2C%3C%2Fp%3E%0A%3Cp%20class%3D%22poet2%22%3Ea%20poisonous%20viper%20along%20the%20path%3C%2Fp%3E%0A%3Cp%20class%3D%22poet1%22%3Ethat%20bites%20the%20horse%26%23x2019%3Bs%20hooves%3C%2Fp%3E%0A%3Cp%20class%3D%22poet2%22%3Eso%20its%20rider%20is%20thrown%20off.%3C%2Fp%3E%0A%3C%2Fverse_export%3E%3Cverse_export%20orig%3D%22gene_49_18%22%20bk%3D%22gene%22%20ch%3D%2249%22%20vn%3D%2218%22%3E%0A%3Cp%20class%3D%22poet1-vn%22%3E%3Cspan%20class%3D%22vn%22%3E18%3C%2Fspan%3EI%20trust%20in%20you%20for%20salvation%2C%20O%26%23xA0%3B%3Cspan%20class%3D%22sc%22%3ELord%3C%2Fspan%3E!%3C%2Fp%3E%0A%3C%2Fverse_export%3E%3Cverse_export%20orig%3D%22gene_49_19%22%20bk%3D%22gene%22%20ch%3D%2249%22%20vn%3D%2219%22%3E%0A%3Cp%20class%3D%22poet1-vn-sp%22%3E%3Cspan%20class%3D%22vn%22%3E19%3C%2Fspan%3E%26%23x201C%3BGad%20will%20be%20attacked%20by%20marauding%20bands%2C%3C%2Fp%3E%0A%3Cp%20class%3D%22poet2%22%3Ebut%20he%20will%20attack%20them%20when%20they%20retreat.%3C%2Fp%3E%0A%3C%2Fverse_export%3E%3Cverse_export%20orig%3D%22gene_49_20%22%20bk%3D%22gene%22%20ch%3D%2249%22%20vn%3D%2220%22%3E%0A%3Cp%20class%3D%22poet1-vn-sp%22%3E%3Cspan%20class%3D%22vn%22%3E20%3C%2Fspan%3E%26%23x201C%3BAsher%20will%20dine%20on%20rich%20foods%3C%2Fp%3E%0A%3Cp%20class%3D%22poet2%22%3Eand%20produce%20food%20fit%20for%20kings.%3C%2Fp%3E%0A%3C%2Fverse_export%3E%3Cverse_export%20orig%3D%22gene_49_21%22%20bk%3D%22gene%22%20ch%3D%2249%22%20vn%3D%2221%22%3E%0A%3Cp%20class%3D%22poet1-vn-sp%22%3E%3Cspan%20class%3D%22vn%22%3E21%3C%2Fspan%3E%26%23x201C%3BNaphtali%20is%20a%20doe%20set%20free%3C%2Fp%3E%0A%3Cp%20class%3D%22poet2%22%3Ethat%20bears%20beautiful%20fawns.%3C%2Fp%3E%0A%3C%2Fverse_export%3E%3Cverse_export%20orig%3D%22gene_49_22%22%20bk%3D%22gene%22%20ch%3D%2249%22%20vn%3D%2222%22%3E%0A%3Cp%20class%3D%22poet1-vn-sp%22%3E%3Cspan%20class%3D%22vn%22%3E22%3C%2Fspan%3E%26%23x201C%3BJoseph%20is%20the%20foal%20of%20a%20wild%20donkey%2C%3C%2Fp%3E%0A%3Cp%20class%3D%22poet2%22%3Ethe%20foal%20of%20a%20wild%20donkey%20at%20a%20spring%26%23x2014%3B%3C%2Fp%3E%0A%3Cp%20class%3D%22poet2%22%3Eone%20of%20the%20wild%20donkeys%20on%20the%20ridge.%3Ca%20class%3D%22a-tn%22%3E*%3C%2Fa%3E%3Cspan%20class%3D%22tn%22%3E%3Cspan%20class%3D%22tn-ref%22%3E49%3A22%3C%2Fspan%3E%20Or%20%3Cem%3EJoseph%20is%20a%20fruitful%20tree%2C%20%2F%20a%20fruitful%20tree%20beside%20a%20spring.%20%2F%20His%20branches%20reach%20over%20the%20wall.%3C%2Fem%3E%20The%20meaning%20of%20the%20Hebrew%20is%20uncertain.%3C%2Fspan%3E%3C%2Fp%3E%0A%3C%2Fverse_export%3E%3Cverse_export%20orig%3D%22gene_49_23%22%20bk%3D%22gene%22%20ch%3D%2249%22%20vn%3D%2223%22%3E%0A%3Cp%20class%3D%22poet1-vn%22%3E%3Cspan%20class%3D%22vn%22%3E23%3C%2Fspan%3EArchers%20attacked%20him%20savagely%3B%3C%2Fp%3E%0A%3Cp%20class%3D%22poet2%22%3Ethey%20shot%20at%20him%20and%20harassed%20him.%3C%2Fp%3E%0A%3C%2Fverse_export%3E%3Cverse_export%20orig%3D%22gene_49_24%22%20bk%3D%22gene%22%20ch%3D%2249%22%20vn%3D%2224%22%3E%0A%3Cp%20class%3D%22poet1-vn%22%3E%3Cspan%20class%3D%22vn%22%3E24%3C%2Fspan%3EBut%20his%20bow%20remained%20taut%2C%3C%2Fp%3E%0A%3Cp%20class%3D%22poet2%22%3Eand%20his%20arms%20were%20strengthened%3C%2Fp%3E%0A%3Cp%20class%3D%22poet1%22%3Eby%20the%20hands%20of%20the%20Mighty%20One%20of%20Jacob%2C%3C%2Fp%3E%0A%3Cp%20class%3D%22poet2%22%3Eby%20the%20Shepherd%2C%20the%20Rock%20of%20Israel.%3C%2Fp%3E%0A%3C%2Fverse_export%3E%3Cverse_export%20orig%3D%22gene_49_25%22%20bk%3D%22gene%22%20ch%3D%2249%22%20vn%3D%2225%22%3E%0A%3Cp%20class%3D%22poet1-vn%22%3E%3Cspan%20class%3D%22vn%22%3E25%3C%2Fspan%3EMay%20the%20God%20of%20your%20father%20help%20you%3B%3C%2Fp%3E%0A%3Cp%20class%3D%22poet2%22%3Emay%20the%20Almighty%20bless%20you%3C%2Fp%3E%0A%3Cp%20class%3D%22poet1%22%3Ewith%20the%20blessings%20of%20the%20heavens%20above%2C%3C%2Fp%3E%0A%3Cp%20class%3D%22poet2%22%3Eand%20blessings%20of%20the%20watery%20depths%20below%2C%3C%2Fp%3E%0A%3Cp%20class%3D%22poet2%22%3Eand%20blessings%20of%20the%20breasts%20and%20womb.%3C%2Fp%3E%0A%3C%2Fverse_export%3E%3Cverse_export%20orig%3D%22gene_49_26%22%20bk%3D%22gene%22%20ch%3D%2249%22%20vn%3D%2226%22%3E%0A%3Cp%20class%3D%22poet1-vn%22%3E%3Cspan%20class%3D%22vn%22%3E26%3C%2Fspan%3EMay%20my%20fatherly%20blessings%20on%20you%3C%2Fp%3E%0A%3Cp%20class%3D%22poet2%22%3Esurpass%20the%20blessings%20of%20my%20ancestors%2C%3Ca%20class%3D%22a-tn%22%3E*%3C%2Fa%3E%3Cspan%20class%3D%22tn%22%3E%3Cspan%20class%3D%22tn-ref%22%3E49%3A26%3C%2Fspan%3E%20Or%20%3Cem%3Eof%20the%20ancient%20mountains.%3C%2Fem%3E%3C%2Fspan%3E%3C%2Fp%3E%0A%3Cp%20class%3D%22poet2%22%3Ereaching%20to%20the%20heights%20of%20the%20eternal%20hills.%3C%2Fp%3E%0A%3Cp%20class%3D%22poet1%22%3EMay%20these%20blessings%20rest%20on%20the%20head%20of%20Joseph%2C%3C%2Fp%3E%0A%3Cp%20class%3D%22poet2%22%3Ewho%20is%20a%20prince%20among%20his%20brothers.%3C%2Fp%3E%0A%3C%2Fverse_export%3E%3Cverse_export%20orig%3D%22gene_49_27%22%20bk%3D%22gene%22%20ch%3D%2249%22%20vn%3D%2227%22%3E%0A%3Cp%20class%3D%22poet1-vn-sp%22%3E%3Cspan%20class%3D%22vn%22%3E27%3C%2Fspan%3E%26%23x201C%3BBenjamin%20is%20a%20ravenous%20wolf%2C%3C%2Fp%3E%0A%3Cp%20class%3D%22poet2%22%3Edevouring%20his%20enemies%20in%20the%20morning%3C%2Fp%3E%0A%3Cp%20class%3D%22poet2%22%3Eand%20dividing%20his%20plunder%20in%20the%20evening.%26%23x201D%3B%3C%2Fp%3E%0A%3C%2Fverse_export%3E%3Cverse_export%20orig%3D%22gene_49_28%22%20bk%3D%22gene%22%20ch%3D%2249%22%20vn%3D%2228%22%3E%0A%3Cp%20class%3D%22body-sp%22%3E%3Cspan%20class%3D%22vn%22%3E28%3C%2Fspan%3EThese%20are%20the%20twelve%20tribes%20of%20Israel%2C%20and%20this%20is%20what%20their%20father%20said%20as%20he%20told%20his%20sons%20good-bye.%20He%20blessed%20each%20one%20with%20an%20appropriate%20message.%3C%2Fp%3E%0A%3C%2Fverse_export%3E%3Cverse_export%20orig%3D%22gene_49_29%22%20bk%3D%22gene%22%20ch%3D%2249%22%20vn%3D%2229%22%3E%0A%3Cp%20class%3D%22subhead%22%3EJacob%26%23x2019%3Bs%20Death%20and%20Burial%3C%2Fp%3E%0A%3Cp%20class%3D%22body-hd%22%3E%3Cspan%20class%3D%22vn%22%3E29%3C%2Fspan%3EThen%20Jacob%20instructed%20them%2C%20%26%23x201C%3BSoon%20I%20will%20die%20and%20join%20my%20ancestors.%20Bury%20me%20with%20my%20father%20and%20grandfather%20in%20the%20cave%20in%20the%20field%20of%20Ephron%20the%20Hittite.%20%3Cverse_export%20orig%3D%22gene_49_30%22%20bk%3D%22gene%22%20ch%3D%2249%22%20vn%3D%2230%22%3E%3Cspan%20class%3D%22vn%22%3E30%3C%2Fspan%3EThis%20is%20the%20cave%20in%20the%20field%20of%20Machpelah%2C%20near%20Mamre%20in%20Canaan%2C%20that%20Abraham%20bought%20from%20Ephron%20the%20Hittite%20as%20a%20permanent%20burial%20site.%20%3C%2Fverse_export%3E%3Cverse_export%20orig%3D%22gene_49_31%22%20bk%3D%22gene%22%20ch%3D%2249%22%20vn%3D%2231%22%3E%3Cspan%20class%3D%22vn%22%3E31%3C%2Fspan%3EThere%20Abraham%20and%20his%20wife%20Sarah%20are%20buried.%20There%20Isaac%20and%20his%20wife%2C%20Rebekah%2C%20are%20buried.%20And%20there%20I%20buried%20Leah.%20%3C%2Fverse_export%3E%3Cverse_export%20orig%3D%22gene_49_32%22%20bk%3D%22gene%22%20ch%3D%2249%22%20vn%3D%2232%22%3E%3Cspan%20class%3D%22vn%22%3E32%3C%2Fspan%3EIt%20is%20the%20plot%20of%20land%20and%20the%20cave%20that%20my%20grandfather%20Abraham%20bought%20from%20the%20Hittites.%26%23x201D%3B%3C%2Fverse_export%3E%3C%2Fp%3E%3Cp%3E%0A%3Cverse_export%20orig%3D%22gene_49_33%22%20bk%3D%22gene%22%20ch%3D%2249%22%20vn%3D%2233%22%3E%0A%3C%2Fverse_export%3E%3C%2Fp%3E%3Cp%20class%3D%22body%22%3E%3Cspan%20class%3D%22vn%22%3E33%3C%2Fspan%3EWhen%20Jacob%20had%20finished%20this%20charge%20to%20his%20sons%2C%20he%20drew%20his%20feet%20into%20the%20bed%2C%20breathed%20his%20last%2C%20and%20joined%20his%20ancestors%20in%20death.%3C%2Fp%3E%0A%3C%2Fverse_export%3E%3C%2Fsection%3E%3C%2Fdiv%3E"
        },
        {
            "id": "nt-passage",
            "type": "passage",
            "title": "New Testament Reading",
            "api_nlt_to_ref": "Matthew.15:29-16:12",
            "value": "%3Cdiv%20class%3D%22%20NLT%20NLT%20BibleText%20section%22%3E%3Csection%3E%3Ch2%20class%3D%22bk_ch_vs_header%22%3EMatthew%2015%3A29-16%3A12%2C%20NLT%3C%2Fh2%3E%3Cverse_export%20orig%3D%22matt_15_29%22%20bk%3D%22matt%22%20ch%3D%2215%22%20vn%3D%2229%22%3E%0A%3Cp%20class%3D%22subhead%22%3EJesus%20Heals%20Many%20People%3C%2Fp%3E%0A%3Cp%20class%3D%22body-hd%22%3E%3Cspan%20class%3D%22vn%22%3E29%3C%2Fspan%3EJesus%20returned%20to%20the%20Sea%20of%20Galilee%20and%20climbed%20a%20hill%20and%20sat%20down.%20%3Cverse_export%20orig%3D%22matt_15_30%22%20bk%3D%22matt%22%20ch%3D%2215%22%20vn%3D%2230%22%3E%3Cspan%20class%3D%22vn%22%3E30%3C%2Fspan%3EA%20vast%20crowd%20brought%20to%20him%20people%20who%20were%20lame%2C%20blind%2C%20crippled%2C%20those%20who%20couldn%26%23x2019%3Bt%20speak%2C%20and%20many%20others.%20They%20laid%20them%20before%20Jesus%2C%20and%20he%20healed%20them%20all.%20%3C%2Fverse_export%3E%3Cverse_export%20orig%3D%22matt_15_31%22%20bk%3D%22matt%22%20ch%3D%2215%22%20vn%3D%2231%22%3E%3Cspan%20class%3D%22vn%22%3E31%3C%2Fspan%3EThe%20crowd%20was%20amazed!%20Those%20who%20hadn%26%23x2019%3Bt%20been%20able%20to%20speak%20were%20talking%2C%20the%20crippled%20were%20made%20well%2C%20the%20lame%20were%20walking%2C%20and%20the%20blind%20could%20see%20again!%20And%20they%20praised%20the%20God%20of%20Israel.%3C%2Fverse_export%3E%3C%2Fp%3E%3Cp%3E%0A%3Cverse_export%20orig%3D%22matt_15_32%22%20bk%3D%22matt%22%20ch%3D%2215%22%20vn%3D%2232%22%3E%0A%3C%2Fverse_export%3E%3C%2Fp%3E%3Cp%20class%3D%22subhead%22%3EJesus%20Feeds%20Four%20Thousand%3C%2Fp%3E%0A%3Cp%20class%3D%22body-hd%22%3E%3Cspan%20class%3D%22vn%22%3E32%3C%2Fspan%3EThen%20Jesus%20called%20his%20disciples%20and%20told%20them%2C%20%3Cspan%20class%3D%22red%22%3E%26%23x201C%3BI%20feel%20sorry%20for%20these%20people.%20They%20have%20been%20here%20with%20me%20for%20three%20days%2C%20and%20they%20have%20nothing%20left%20to%20eat.%20I%20don%26%23x2019%3Bt%20want%20to%20send%20them%20away%20hungry%2C%20or%20they%20will%20faint%20along%20the%20way.%26%23x201D%3B%3C%2Fspan%3E%3C%2Fp%3E%0A%3C%2Fverse_export%3E%3Cverse_export%20orig%3D%22matt_15_33%22%20bk%3D%22matt%22%20ch%3D%2215%22%20vn%3D%2233%22%3E%0A%3Cp%20class%3D%22body%22%3E%3Cspan%20class%3D%22vn%22%3E33%3C%2Fspan%3EThe%20disciples%20replied%2C%20%26%23x201C%3BWhere%20would%20we%20get%20enough%20food%20here%20in%20the%20wilderness%20for%20such%20a%20huge%20crowd%3F%26%23x201D%3B%3C%2Fp%3E%0A%3C%2Fverse_export%3E%3Cverse_export%20orig%3D%22matt_15_34%22%20bk%3D%22matt%22%20ch%3D%2215%22%20vn%3D%2234%22%3E%0A%3Cp%20class%3D%22body%22%3E%3Cspan%20class%3D%22vn%22%3E34%3C%2Fspan%3EJesus%20asked%2C%20%3Cspan%20class%3D%22red%22%3E%26%23x201C%3BHow%20much%20bread%20do%20you%20have%3F%26%23x201D%3B%3C%2Fspan%3E%3C%2Fp%3E%0A%3Cp%20class%3D%22body%22%3EThey%20replied%2C%20%26%23x201C%3BSeven%20loaves%2C%20and%20a%20few%20small%20fish.%26%23x201D%3B%3C%2Fp%3E%0A%3C%2Fverse_export%3E%3Cverse_export%20orig%3D%22matt_15_35%22%20bk%3D%22matt%22%20ch%3D%2215%22%20vn%3D%2235%22%3E%0A%3Cp%20class%3D%22body%22%3E%3Cspan%20class%3D%22vn%22%3E35%3C%2Fspan%3ESo%20Jesus%20told%20all%20the%20people%20to%20sit%20down%20on%20the%20ground.%20%3Cverse_export%20orig%3D%22matt_15_36%22%20bk%3D%22matt%22%20ch%3D%2215%22%20vn%3D%2236%22%3E%3Cspan%20class%3D%22vn%22%3E36%3C%2Fspan%3EThen%20he%20took%20the%20seven%20loaves%20and%20the%20fish%2C%20thanked%20God%20for%20them%2C%20and%20broke%20them%20into%20pieces.%20He%20gave%20them%20to%20the%20disciples%2C%20who%20distributed%20the%20food%20to%20the%20crowd.%3C%2Fverse_export%3E%3C%2Fp%3E%3Cp%3E%0A%3Cverse_export%20orig%3D%22matt_15_37%22%20bk%3D%22matt%22%20ch%3D%2215%22%20vn%3D%2237%22%3E%0A%3C%2Fverse_export%3E%3C%2Fp%3E%3Cp%20class%3D%22body%22%3E%3Cspan%20class%3D%22vn%22%3E37%3C%2Fspan%3EThey%20all%20ate%20as%20much%20as%20they%20wanted.%20Afterward%2C%20the%20disciples%20picked%20up%20seven%20large%20baskets%20of%20leftover%20food.%20%3Cverse_export%20orig%3D%22matt_15_38%22%20bk%3D%22matt%22%20ch%3D%2215%22%20vn%3D%2238%22%3E%3Cspan%20class%3D%22vn%22%3E38%3C%2Fspan%3EThere%20were%204%2C000%20men%20who%20were%20fed%20that%20day%2C%20in%20addition%20to%20all%20the%20women%20and%20children.%20%3C%2Fverse_export%3E%3Cverse_export%20orig%3D%22matt_15_39%22%20bk%3D%22matt%22%20ch%3D%2215%22%20vn%3D%2239%22%3E%3Cspan%20class%3D%22vn%22%3E39%3C%2Fspan%3EThen%20Jesus%20sent%20the%20people%20home%2C%20and%20he%20got%20into%20a%20boat%20and%20crossed%20over%20to%20the%20region%20of%20Magadan.%3C%2Fverse_export%3E%3C%2Fp%3E%3Cp%3E%0A%3Cverse_export%20orig%3D%22matt_16_1%22%20bk%3D%22matt%22%20ch%3D%2216%22%20vn%3D%221%22%3E%0A%3C%2Fverse_export%3E%3C%2Fp%3E%3Cp%20class%3D%22chapter-number%22%3E%3Cspan%20class%3D%22cw%22%3EMatthew%3C%2Fspan%3E%26%23xA0%3B%3Cspan%20class%3D%22cw_ch%22%3E16%3C%2Fspan%3E%3C%2Fp%3E%0A%3Cp%20class%3D%22subhead%22%3ELeaders%20Demand%20a%20Miraculous%20Sign%3C%2Fp%3E%0A%3Cp%20class%3D%22body-ch-hd%22%3E%3Cspan%20class%3D%22vn%22%3E1%3C%2Fspan%3EOne%20day%20the%20Pharisees%20and%20Sadducees%20came%20to%20test%20Jesus%2C%20demanding%20that%20he%20show%20them%20a%20miraculous%20sign%20from%20heaven%20to%20prove%20his%20authority.%3C%2Fp%3E%0A%3C%2Fverse_export%3E%3Cverse_export%20orig%3D%22matt_16_2%22%20bk%3D%22matt%22%20ch%3D%2216%22%20vn%3D%222%22%3E%0A%3Cp%20class%3D%22body%22%3E%3Cspan%20class%3D%22vn%22%3E2%3C%2Fspan%3EHe%20replied%2C%20%3Cspan%20class%3D%22red%22%3E%26%23x201C%3BYou%20know%20the%20saying%2C%20%26%23x2018%3BRed%20sky%20at%20night%20means%20fair%20weather%20tomorrow%3B%3C%2Fspan%3E%20%3Cverse_export%20orig%3D%22matt_16_3%22%20bk%3D%22matt%22%20ch%3D%2216%22%20vn%3D%223%22%3E%3Cspan%20class%3D%22vn%22%3E3%3C%2Fspan%3E%3Cspan%20class%3D%22red%22%3Ered%20sky%20in%20the%20morning%20means%20foul%20weather%20all%20day.%26%23x2019%3B%20You%20know%20how%20to%20interpret%20the%20weather%20signs%20in%20the%20sky%2C%20but%20you%20don%26%23x2019%3Bt%20know%20how%20to%20interpret%20the%20signs%20of%20the%20times!%3Ca%20class%3D%22a-tn%22%3E*%3C%2Fa%3E%3Cspan%20class%3D%22tn%22%3E%3Cspan%20class%3D%22tn-ref%22%3E16%3A2-3%3C%2Fspan%3E%20Several%20manuscripts%20do%20not%20include%20any%20of%20the%20words%20in%2016%3A2-3%20after%20%3Cem%3EHe%20replied.%3C%2Fem%3E%3C%2Fspan%3E%3C%2Fspan%3E%20%3C%2Fverse_export%3E%3Cverse_export%20orig%3D%22matt_16_4%22%20bk%3D%22matt%22%20ch%3D%2216%22%20vn%3D%224%22%3E%3Cspan%20class%3D%22vn%22%3E4%3C%2Fspan%3E%3Cspan%20class%3D%22red%22%3EOnly%20an%20evil%2C%20adulterous%20generation%20would%20demand%20a%20miraculous%20sign%2C%20but%20the%20only%20sign%20I%20will%20give%20them%20is%20the%20sign%20of%20the%20prophet%20Jonah.%3Ca%20class%3D%22a-tn%22%3E*%3C%2Fa%3E%3Cspan%20class%3D%22tn%22%3E%3Cspan%20class%3D%22tn-ref%22%3E16%3A4%3C%2Fspan%3E%20Greek%20%3Cem%3Ethe%20sign%20of%20Jonah.%3C%2Fem%3E%3C%2Fspan%3E%26%23x201D%3B%3C%2Fspan%3E%20Then%20Jesus%20left%20them%20and%20went%20away.%3C%2Fverse_export%3E%3C%2Fp%3E%3Cp%3E%0A%3Cverse_export%20orig%3D%22matt_16_5%22%20bk%3D%22matt%22%20ch%3D%2216%22%20vn%3D%225%22%3E%0A%3C%2Fverse_export%3E%3C%2Fp%3E%3Cp%20class%3D%22subhead%22%3EYeast%20of%20the%20Pharisees%20and%20Sadducees%3C%2Fp%3E%0A%3Cp%20class%3D%22body-hd%22%3E%3Cspan%20class%3D%22vn%22%3E5%3C%2Fspan%3ELater%2C%20after%20they%20crossed%20to%20the%20other%20side%20of%20the%20lake%2C%20the%20disciples%20discovered%20they%20had%20forgotten%20to%20bring%20any%20bread.%20%3Cverse_export%20orig%3D%22matt_16_6%22%20bk%3D%22matt%22%20ch%3D%2216%22%20vn%3D%226%22%3E%3Cspan%20class%3D%22vn%22%3E6%3C%2Fspan%3E%3Cspan%20class%3D%22red%22%3E%26%23x201C%3BWatch%20out!%26%23x201D%3B%3C%2Fspan%3E%20Jesus%20warned%20them.%20%3Cspan%20class%3D%22red%22%3E%26%23x201C%3BBeware%20of%20the%20yeast%20of%20the%20Pharisees%20and%20Sadducees.%26%23x201D%3B%3C%2Fspan%3E%3C%2Fverse_export%3E%3C%2Fp%3E%3Cp%3E%0A%3Cverse_export%20orig%3D%22matt_16_7%22%20bk%3D%22matt%22%20ch%3D%2216%22%20vn%3D%227%22%3E%0A%3C%2Fverse_export%3E%3C%2Fp%3E%3Cp%20class%3D%22body%22%3E%3Cspan%20class%3D%22vn%22%3E7%3C%2Fspan%3EAt%20this%20they%20began%20to%20argue%20with%20each%20other%20because%20they%20hadn%26%23x2019%3Bt%20brought%20any%20bread.%20%3Cverse_export%20orig%3D%22matt_16_8%22%20bk%3D%22matt%22%20ch%3D%2216%22%20vn%3D%228%22%3E%3Cspan%20class%3D%22vn%22%3E8%3C%2Fspan%3EJesus%20knew%20what%20they%20were%20saying%2C%20so%20he%20said%2C%20%3Cspan%20class%3D%22red%22%3E%26%23x201C%3BYou%20have%20so%20little%20faith!%20Why%20are%20you%20arguing%20with%20each%20other%20about%20having%20no%20bread%3F%3C%2Fspan%3E%20%3C%2Fverse_export%3E%3Cverse_export%20orig%3D%22matt_16_9%22%20bk%3D%22matt%22%20ch%3D%2216%22%20vn%3D%229%22%3E%3Cspan%20class%3D%22vn%22%3E9%3C%2Fspan%3E%3Cspan%20class%3D%22red%22%3EDon%26%23x2019%3Bt%20you%20understand%20even%20yet%3F%20Don%26%23x2019%3Bt%20you%20remember%20the%205%2C000%20I%20fed%20with%20five%20loaves%2C%20and%20the%20baskets%20of%20leftovers%20you%20picked%20up%3F%3C%2Fspan%3E%20%3C%2Fverse_export%3E%3Cverse_export%20orig%3D%22matt_16_10%22%20bk%3D%22matt%22%20ch%3D%2216%22%20vn%3D%2210%22%3E%3Cspan%20class%3D%22vn%22%3E10%3C%2Fspan%3E%3Cspan%20class%3D%22red%22%3EOr%20the%204%2C000%20I%20fed%20with%20seven%20loaves%2C%20and%20the%20large%20baskets%20of%20leftovers%20you%20picked%20up%3F%3C%2Fspan%3E%20%3C%2Fverse_export%3E%3Cverse_export%20orig%3D%22matt_16_11%22%20bk%3D%22matt%22%20ch%3D%2216%22%20vn%3D%2211%22%3E%3Cspan%20class%3D%22vn%22%3E11%3C%2Fspan%3E%3Cspan%20class%3D%22red%22%3EWhy%20can%26%23x2019%3Bt%20you%20understand%20that%20I%26%23x2019%3Bm%20not%20talking%20about%20bread%3F%20So%20again%20I%20say%2C%20%26%23x2018%3BBeware%20of%20the%20yeast%20of%20the%20Pharisees%20and%20Sadducees.%26%23x2019%3B%26%23x201D%3B%3C%2Fspan%3E%3C%2Fverse_export%3E%3C%2Fp%3E%3Cp%3E%0A%3Cverse_export%20orig%3D%22matt_16_12%22%20bk%3D%22matt%22%20ch%3D%2216%22%20vn%3D%2212%22%3E%0A%3C%2Fverse_export%3E%3C%2Fp%3E%3Cp%20class%3D%22body%22%3E%3Cspan%20class%3D%22vn%22%3E12%3C%2Fspan%3EThen%20at%20last%20they%20understood%20that%20he%20wasn%26%23x2019%3Bt%20speaking%20about%20the%20yeast%20in%20bread%2C%20but%20about%20the%20deceptive%20teaching%20of%20the%20Pharisees%20and%20Sadducees.%3C%2Fp%3E%0A%3C%2Fverse_export%3E%3C%2Fsection%3E%3C%2Fdiv%3E"
        },
        {
            "id": "ps-passage",
            "type": "passage",
            "title": "Psalms Reading",
            "api_nlt_to_ref": "Psalms.20:1-9",
            "value": "%3Cdiv%20class%3D%22%20NLT%20NLT%20BibleText%20section%22%3E%3Csection%3E%3Ch2%20class%3D%22bk_ch_vs_header%22%3EPsalm%2020%3A1-9%2C%20NLT%3C%2Fh2%3E%3Cverse_export%20orig%3D%22psal_20_1%22%20bk%3D%22psal%22%20ch%3D%2220%22%20vn%3D%221%22%3E%0A%3Cp%20class%3D%22chapter-number%22%3E%3Cspan%20class%3D%22cw%22%3EPsalm%3C%2Fspan%3E%26%23xA0%3B%3Cspan%20class%3D%22cw_ch%22%3E20%3C%2Fspan%3E%3C%2Fp%3E%0A%3Cp%20class%3D%22psa-title%22%3EFor%20the%20choir%20director%3A%20A%20psalm%20of%20David.%3C%2Fp%3E%0A%3Cp%20class%3D%22poet1-vn-sp%22%3E%3Cspan%20class%3D%22vn%22%3E1%3C%2Fspan%3EIn%20times%20of%20trouble%2C%20may%20the%20%3Cspan%20class%3D%22sc%22%3ELord%3C%2Fspan%3E%20answer%20your%20cry.%3C%2Fp%3E%0A%3Cp%20class%3D%22poet2%22%3EMay%20the%20name%20of%20the%20God%20of%20Jacob%20keep%20you%20safe%20from%20all%20harm.%3C%2Fp%3E%0A%3C%2Fverse_export%3E%3Cverse_export%20orig%3D%22psal_20_2%22%20bk%3D%22psal%22%20ch%3D%2220%22%20vn%3D%222%22%3E%0A%3Cp%20class%3D%22poet1-vn%22%3E%3Cspan%20class%3D%22vn%22%3E2%3C%2Fspan%3EMay%20he%20send%20you%20help%20from%20his%20sanctuary%3C%2Fp%3E%0A%3Cp%20class%3D%22poet2%22%3Eand%20strengthen%20you%20from%20Jerusalem.%3Ca%20class%3D%22a-tn%22%3E*%3C%2Fa%3E%3Cspan%20class%3D%22tn%22%3E%3Cspan%20class%3D%22tn-ref%22%3E20%3A2%3C%2Fspan%3E%20Hebrew%20%3Cem%3EZion.%3C%2Fem%3E%3C%2Fspan%3E%3C%2Fp%3E%0A%3C%2Fverse_export%3E%3Cverse_export%20orig%3D%22psal_20_3%22%20bk%3D%22psal%22%20ch%3D%2220%22%20vn%3D%223%22%3E%0A%3Cp%20class%3D%22poet1-vn%22%3E%3Cspan%20class%3D%22vn%22%3E3%3C%2Fspan%3EMay%20he%20remember%20all%20your%20gifts%3C%2Fp%3E%0A%3Cp%20class%3D%22poet2%22%3Eand%20look%20favorably%20on%20your%20burnt%20offerings.%3C%2Fp%3E%0A%3Cp%20class%3D%22selah%22%3EInterlude%3C%2Fp%3E%0A%3C%2Fverse_export%3E%3Cverse_export%20orig%3D%22psal_20_4%22%20bk%3D%22psal%22%20ch%3D%2220%22%20vn%3D%224%22%3E%0A%3Cp%20class%3D%22poet1-vn-sp%22%3E%3Cspan%20class%3D%22vn%22%3E4%3C%2Fspan%3EMay%20he%20grant%20your%20heart%26%23x2019%3Bs%20desires%3C%2Fp%3E%0A%3Cp%20class%3D%22poet2%22%3Eand%20make%20all%20your%20plans%20succeed.%3C%2Fp%3E%0A%3C%2Fverse_export%3E%3Cverse_export%20orig%3D%22psal_20_5%22%20bk%3D%22psal%22%20ch%3D%2220%22%20vn%3D%225%22%3E%0A%3Cp%20class%3D%22poet1-vn%22%3E%3Cspan%20class%3D%22vn%22%3E5%3C%2Fspan%3EMay%20we%20shout%20for%20joy%20when%20we%20hear%20of%20your%20victory%3C%2Fp%3E%0A%3Cp%20class%3D%22poet2%22%3Eand%20raise%20a%20victory%20banner%20in%20the%20name%20of%20our%20God.%3C%2Fp%3E%0A%3Cp%20class%3D%22poet1%22%3EMay%20the%20%3Cspan%20class%3D%22sc%22%3ELord%3C%2Fspan%3E%20answer%20all%20your%20prayers.%3C%2Fp%3E%0A%3C%2Fverse_export%3E%3Cverse_export%20orig%3D%22psal_20_6%22%20bk%3D%22psal%22%20ch%3D%2220%22%20vn%3D%226%22%3E%0A%3Cp%20class%3D%22poet1-vn-sp%22%3E%3Cspan%20class%3D%22vn%22%3E6%3C%2Fspan%3ENow%20I%20know%20that%20the%20%3Cspan%20class%3D%22sc%22%3ELord%3C%2Fspan%3E%20rescues%20his%20anointed%20king.%3C%2Fp%3E%0A%3Cp%20class%3D%22poet2%22%3EHe%20will%20answer%20him%20from%20his%20holy%20heaven%3C%2Fp%3E%0A%3Cp%20class%3D%22poet2%22%3Eand%20rescue%20him%20by%20his%20great%20power.%3C%2Fp%3E%0A%3C%2Fverse_export%3E%3Cverse_export%20orig%3D%22psal_20_7%22%20bk%3D%22psal%22%20ch%3D%2220%22%20vn%3D%227%22%3E%0A%3Cp%20class%3D%22poet1-vn%22%3E%3Cspan%20class%3D%22vn%22%3E7%3C%2Fspan%3ESome%20nations%20boast%20of%20their%20chariots%20and%20horses%2C%3C%2Fp%3E%0A%3Cp%20class%3D%22poet2%22%3Ebut%20we%20boast%20in%20the%20name%20of%20the%20%3Cspan%20class%3D%22sc%22%3ELord%3C%2Fspan%3E%20our%20God.%3C%2Fp%3E%0A%3C%2Fverse_export%3E%3Cverse_export%20orig%3D%22psal_20_8%22%20bk%3D%22psal%22%20ch%3D%2220%22%20vn%3D%228%22%3E%0A%3Cp%20class%3D%22poet1-vn%22%3E%3Cspan%20class%3D%22vn%22%3E8%3C%2Fspan%3EThose%20nations%20will%20fall%20down%20and%20collapse%2C%3C%2Fp%3E%0A%3Cp%20class%3D%22poet2%22%3Ebut%20we%20will%20rise%20up%20and%20stand%20firm.%3C%2Fp%3E%0A%3C%2Fverse_export%3E%3Cverse_export%20orig%3D%22psal_20_9%22%20bk%3D%22psal%22%20ch%3D%2220%22%20vn%3D%229%22%3E%0A%3Cp%20class%3D%22poet1-vn-sp%22%3E%3Cspan%20class%3D%22vn%22%3E9%3C%2Fspan%3EGive%20victory%20to%20our%20king%2C%20O%26%23xA0%3B%3Cspan%20class%3D%22sc%22%3ELord%3C%2Fspan%3E!%3C%2Fp%3E%0A%3Cp%20class%3D%22poet2%22%3EAnswer%20our%20cry%20for%20help.%3C%2Fp%3E%0A%3C%2Fverse_export%3E%3C%2Fsection%3E%3C%2Fdiv%3E"
        },
        {
            "id": "pr-passage",
            "type": "passage",
            "title": "Proverbs Reading",
            "api_nlt_to_ref": "Proverbs.4:20-27",
            "value": "%3Cdiv%20class%3D%22%20NLT%20NLT%20BibleText%20section%22%3E%3Csection%3E%3Ch2%20class%3D%22bk_ch_vs_header%22%3EProverbs%204%3A20-27%2C%20NLT%3C%2Fh2%3E%3Cverse_export%20orig%3D%22prov_4_20%22%20bk%3D%22prov%22%20ch%3D%224%22%20vn%3D%2220%22%3E%0A%3Cp%20class%3D%22poet1-vn-sp%22%3E%3Cspan%20class%3D%22vn%22%3E20%3C%2Fspan%3EMy%20child%2C%20pay%20attention%20to%20what%20I%20say.%3C%2Fp%3E%0A%3Cp%20class%3D%22poet2%22%3EListen%20carefully%20to%20my%20words.%3C%2Fp%3E%0A%3C%2Fverse_export%3E%3Cverse_export%20orig%3D%22prov_4_21%22%20bk%3D%22prov%22%20ch%3D%224%22%20vn%3D%2221%22%3E%0A%3Cp%20class%3D%22poet1-vn%22%3E%3Cspan%20class%3D%22vn%22%3E21%3C%2Fspan%3EDon%26%23x2019%3Bt%20lose%20sight%20of%20them.%3C%2Fp%3E%0A%3Cp%20class%3D%22poet2%22%3ELet%20them%20penetrate%20deep%20into%20your%20heart%2C%3C%2Fp%3E%0A%3C%2Fverse_export%3E%3Cverse_export%20orig%3D%22prov_4_22%22%20bk%3D%22prov%22%20ch%3D%224%22%20vn%3D%2222%22%3E%0A%3Cp%20class%3D%22poet1-vn%22%3E%3Cspan%20class%3D%22vn%22%3E22%3C%2Fspan%3Efor%20they%20bring%20life%20to%20those%20who%20find%20them%2C%3C%2Fp%3E%0A%3Cp%20class%3D%22poet2%22%3Eand%20healing%20to%20their%20whole%20body.%3C%2Fp%3E%0A%3C%2Fverse_export%3E%3Cverse_export%20orig%3D%22prov_4_23%22%20bk%3D%22prov%22%20ch%3D%224%22%20vn%3D%2223%22%3E%0A%3Cp%20class%3D%22poet1-vn-sp%22%3E%3Cspan%20class%3D%22vn%22%3E23%3C%2Fspan%3EGuard%20your%20heart%20above%20all%20else%2C%3C%2Fp%3E%0A%3Cp%20class%3D%22poet2%22%3Efor%20it%20determines%20the%20course%20of%20your%20life.%3C%2Fp%3E%0A%3C%2Fverse_export%3E%3Cverse_export%20orig%3D%22prov_4_24%22%20bk%3D%22prov%22%20ch%3D%224%22%20vn%3D%2224%22%3E%0A%3Cp%20class%3D%22poet1-vn-sp%22%3E%3Cspan%20class%3D%22vn%22%3E24%3C%2Fspan%3EAvoid%20all%20perverse%20talk%3B%3C%2Fp%3E%0A%3Cp%20class%3D%22poet2%22%3Estay%20away%20from%20corrupt%20speech.%3C%2Fp%3E%0A%3C%2Fverse_export%3E%3Cverse_export%20orig%3D%22prov_4_25%22%20bk%3D%22prov%22%20ch%3D%224%22%20vn%3D%2225%22%3E%0A%3Cp%20class%3D%22poet1-vn-sp%22%3E%3Cspan%20class%3D%22vn%22%3E25%3C%2Fspan%3ELook%20straight%20ahead%2C%3C%2Fp%3E%0A%3Cp%20class%3D%22poet2%22%3Eand%20fix%20your%20eyes%20on%20what%20lies%20before%20you.%3C%2Fp%3E%0A%3C%2Fverse_export%3E%3Cverse_export%20orig%3D%22prov_4_26%22%20bk%3D%22prov%22%20ch%3D%224%22%20vn%3D%2226%22%3E%0A%3Cp%20class%3D%22poet1-vn%22%3E%3Cspan%20class%3D%22vn%22%3E26%3C%2Fspan%3EMark%20out%20a%20straight%20path%20for%20your%20feet%3B%3C%2Fp%3E%0A%3Cp%20class%3D%22poet2%22%3Estay%20on%20the%20safe%20path.%3C%2Fp%3E%0A%3C%2Fverse_export%3E%3Cverse_export%20orig%3D%22prov_4_27%22%20bk%3D%22prov%22%20ch%3D%224%22%20vn%3D%2227%22%3E%0A%3Cp%20class%3D%22poet1-vn%22%3E%3Cspan%20class%3D%22vn%22%3E27%3C%2Fspan%3EDon%26%23x2019%3Bt%20get%20sidetracked%3B%3C%2Fp%3E%0A%3Cp%20class%3D%22poet2%22%3Ekeep%20your%20feet%20from%20following%20evil.%3C%2Fp%3E%0A%3C%2Fverse_export%3E%3C%2Fsection%3E%3C%2Fdiv%3E"
        }
    ]
}